autogen_primordia/__init__.py
autogen_primordia/wrapper.py
autogen_primordia-0.1.0.dist-info/METADATA
autogen_primordia-0.1.0.dist-info/WHEEL
autogen_primordia-0.1.0.dist-info/RECORD
