Metadata-Version: 2.4
Name: autogen-primordia
Version: 0.1.0
Summary: Primordia metering for Microsoft AutoGen
Project-URL: Kernel, https://clearing.kaledge.app
License-Expression: MIT
Requires-Python: >=3.9
Requires-Dist: pyautogen>=0.2.0
